mcp_server_perplexity/__init__.py
mcp_server_perplexity/__main__.py
mcp_server_perplexity/server.py
iflow_mcp_mcp_server_perplexity-0.1.4.dist-info/METADATA
iflow_mcp_mcp_server_perplexity-0.1.4.dist-info/WHEEL
iflow_mcp_mcp_server_perplexity-0.1.4.dist-info/entry_points.txt
iflow_mcp_mcp_server_perplexity-0.1.4.dist-info/licenses/LICENSE
iflow_mcp_mcp_server_perplexity-0.1.4.dist-info/RECORD
