Metadata-Version: 2.4
Name: iflow-mcp_mcp-server-perplexity
Version: 0.1.4
Summary: MCP Server for the Perplexity API.
Project-URL: Homepage, https://github.com/tanigami/mcp-server-perplexity
Project-URL: Repository, https://github.com/tanigami/mcp-server-perplexity
Author-email: Hirofumi Tanigami <tanigami@teps.io>
License-File: LICENSE
Requires-Python: >=3.10
Requires-Dist: mcp>=1.0.0
